{
  "menu": [
    {
      "id": 1,
      "name": "داشبورد",
      "url": "/"
    },
    {
      "id": 2,
      "name": "نقش‌ها",
      "url": "/roles"
    },
    {
      "id": 3,
      "name": "دسته‌بندی محصولات",
      "url": "/categories"
    },
    {
      "id": 4,
      "name": "محصولات",
      "url": "/products"
    },
    {
      "id": 5,
      "name": "تنطیمات",
      "url": "/settings",
      "subMenu": [
        {
          "name": "sub155555555555555"
        },
        {
          "name": "sub2"
        },
        {
          "name": "sub3"
        }
      ]
    }
  ]
}
